flask_sqlalchemy_helpers.py
Flask_SQLAlchemy_Helpers-1.9.1.dist-info/LICENSE
Flask_SQLAlchemy_Helpers-1.9.1.dist-info/METADATA
Flask_SQLAlchemy_Helpers-1.9.1.dist-info/WHEEL
Flask_SQLAlchemy_Helpers-1.9.1.dist-info/top_level.txt
Flask_SQLAlchemy_Helpers-1.9.1.dist-info/RECORD
