Metadata-Version: 2.1
Name: Flask-SQLAlchemy-Helpers
Version: 1.9.1
Summary: Helpers classes and functions to make work with SQLAlchemy and Flask easier and less repetitive (DRY).
Home-page: https://github.com/tonykamillo/Flask-SQLAchemy-Helpers
Author: Tony Kamillo
Author-email: tonykamillo@gmail.com
License: BSD
Platform: any
Classifier: Environment :: Web Environment
Classifier: Intended Audience :: Developers
Classifier: Operating System :: OS Independent
Classifier: Programming Language :: Python
Requires-Dist: Flask
Requires-Dist: SQLAlchemy
Requires-Dist: Flask-SQLAlchemy
